benchmarks/__init__.py
benchmarks/run_all.py
benchmarks/accuracy/__init__.py
benchmarks/accuracy/bead_simulation_sweep.py
benchmarks/accuracy/plot_sweep.py
benchmarks/accuracy/plot_xy_results.py
benchmarks/accuracy/runner.py
benchmarks/accuracy/sweep_loader.py
benchmarks/accuracy/xy_evaluation.py
benchmarks/language/c_runtime.c
benchmarks/language/center_of_mass.c
benchmarks/language/center_of_mass.h
benchmarks/language/center_of_mass.m
benchmarks/language/center_of_mass.rs
benchmarks/language/center_of_mass_cpp.cpp
benchmarks/language/center_of_mass_cpp.h
benchmarks/language/center_of_mass_impl.h
benchmarks/language/cpp_runtime.cpp
benchmarks/language/matlab_runtime.m
benchmarks/language/python_runtime.py
benchmarks/language/rust_runtime.rs
benchmarks/speed/__init__.py
benchmarks/speed/benchmark_auto_conv.py
benchmarks/speed/benchmark_auto_conv_multiline.py
benchmarks/speed/benchmark_auto_conv_multiline_sub_pixel.py
benchmarks/speed/benchmark_auto_conv_sub_pixel.py
benchmarks/speed/benchmark_center_of_mass.py
benchmarks/speed/benchmark_fft_profile.py
benchmarks/speed/benchmark_lookup_z.py
benchmarks/speed/benchmark_qi.py
benchmarks/speed/benchmark_radial_profile.py
benchmarks/speed/confbenchmarks.py
benchmarks/speed/cpu_benchmark.py
benchmarks/speed/log_utils.py
benchmarks/speed/plot_benchmarks.py
benchmarks/speed/run_all.py
magtrack/__init__.py
magtrack/_cupy.py
magtrack/core.py
magtrack/simulation.py
magtrack-0.7.6.dist-info/licenses/license
magtrack-0.7.6.dist-info/METADATA
magtrack-0.7.6.dist-info/WHEEL
magtrack-0.7.6.dist-info/entry_points.txt
magtrack-0.7.6.dist-info/top_level.txt
magtrack-0.7.6.dist-info/RECORD
